nestipy_cli/__init__.py
nestipy_cli/cli.py
nestipy_cli/config.py
nestipy_cli/handler.py
nestipy_cli/repl.py
nestipy_cli/style.py
nestipy_cli/templates/__init__.py
nestipy_cli/templates/generator.py
nestipy_cli/templates/project/.gitignore
nestipy_cli/templates/project/Dockerfile
nestipy_cli/templates/project/README.md
nestipy_cli/templates/project/__init__.py
nestipy_cli/templates/project/app_controller.py
nestipy_cli/templates/project/app_module.py
nestipy_cli/templates/project/app_service.py
nestipy_cli/templates/project/cli.py
nestipy_cli/templates/project/docker-compose.yml
nestipy_cli/templates/project/main.py
nestipy_cli/templates/project/pyproject.toml
nestipy_cli/templates/project/uv.lock
nestipy_cli/templates/project/logs/.gitignore
nestipy_cli/templates/project/logs/.gitkeep
nestipy_cli/templates/project/src/__init__.py
nestipy_cli/templates/views/command.txt
nestipy_cli/templates/views/controller.txt
nestipy_cli/templates/views/dto.txt
nestipy_cli/templates/views/graphql_module.txt
nestipy_cli/templates/views/graphql_service.txt
nestipy_cli/templates/views/input.txt
nestipy_cli/templates/views/module.txt
nestipy_cli/templates/views/resolver.txt
nestipy_cli/templates/views/service.txt
nestipy_cli/templates/views/single_controller.txt
nestipy_cli/templates/views/single_module.txt
nestipy_cli/templates/views/single_resolver.txt
nestipy_cli/templates/views/single_service.txt
nestipy_cli-0.7.4.dist-info/METADATA
nestipy_cli-0.7.4.dist-info/WHEEL
nestipy_cli-0.7.4.dist-info/entry_points.txt
nestipy_cli-0.7.4.dist-info/RECORD
