Metadata-Version: 2.4
Name: nestipy-cli
Version: 0.7.4
Summary: Nestipy is a Python framework built on top of FastAPI that follows the modular architecture of NestJS
Author-email: tsiresymila <tsiresymila@gmail.com>
Requires-Python: >=3.11
Requires-Dist: aiofile<4,>=3.9.0
Requires-Dist: autoflake<3,>=2.3.1
Requires-Dist: autopep8<3,>=2.1.0
Requires-Dist: click-aliases<2,>=1.0.4
Requires-Dist: click<9,>=8.1.7
Requires-Dist: hachiko<0.5,>=0.4.0
Requires-Dist: isort<6,>=5.13.2
Requires-Dist: minijinja<3,>=2.2.0
Requires-Dist: nestipy>=0.7.5
Requires-Dist: questionary<3,>=2.0.1
Requires-Dist: rich-click<2,>=1.8.3
Requires-Dist: uvicorn[standard]<0.36.0,>=0.35.0
Requires-Dist: watchdog<5,>=4.0.1
Requires-Dist: yaspin<4,>=3.1.0
